{"Anselan Buchanan, Thompson Buchanan v. The United States.": {"id": "102426", "case_name": "Anselan Buchanan, Thompson Buchanan v. The United States.", "date": "1935-03-18", "judges": ""}, "Charles Lee Coggin, Trustee in Bankruptcy of W. Ellison Graham v. Hartford Accident & Indemnity Company, a Connecticut Corporation.": {"id": "102563", "case_name": "Charles Lee Coggin, Trustee in Bankruptcy of W. Ellison Graham v. Hartford Accident & Indemnity Company, a Connecticut Corporation.", "date": "1935-10-14", "judges": ""}, "Youngstown Sheet & Tube Co. v. United States": {"id": "102471", "case_name": "Youngstown Sheet & Tube Co. v. United States", "date": "1935-05-20", "judges": "Roberts"}, "Senior v. Braden": {"id": "102467", "case_name": "Senior v. Braden", "date": "1935-05-20", "judges": "McReynolds"}, "Helvering v. Coleman-Gilbert Associates": {"id": "102522", "case_name": "Helvering v. Coleman-Gilbert Associates", "date": "1935-12-16", "judges": "Hughes"}, "Helvering v. St. Louis Union Trust Co.": {"id": "102488", "case_name": "Helvering v. St. Louis Union Trust Co.", "date": "1935-11-11", "judges": "Sutherland"}, "Nebraska v. Wyoming": {"id": "102430", "case_name": "Nebraska v. Wyoming", "date": "1935-04-01", "judges": "Roberts"}, "The Electric Auto-Lite Company v. P. & D. Manufacturing Company, Inc.": {"id": "102575", "case_name": "The Electric Auto-Lite Company v. P. & D. Manufacturing Company, Inc.", "date": "1935-12-09", "judges": ""}, "William L. Nellis v. Maryland Casualty Company.": {"id": "102559", "case_name": "William L. Nellis v. Maryland Casualty Company.", "date": "1935-10-14", "judges": ""}, "McCrea v. United States": {"id": "102390", "case_name": "McCrea v. United States", "date": "1935-02-18", "judges": "Stone"}, "Wilber Nat. Bank of Oneonta v. United States": {"id": "102373", "case_name": "Wilber Nat. Bank of Oneonta v. United States", "date": "1935-02-04", "judges": "McReynolds"}, "Hopkins Fed. Sav. & Loan Assn. v. Cleary": {"id": "102518", "case_name": "Hopkins Fed. Sav. & Loan Assn. v. Cleary", "date": "1935-12-09", "judges": "Cardozo"}, "Panama Refining Co. v. Ryan": {"id": "102353", "case_name": "Panama Refining Co. v. Ryan", "date": "1935-01-07", "judges": "Hughes"}, "Di Giovanni v. Camden": {"id": "102492", "case_name": "Di Giovanni v. Camden", "date": "1935-11-11", "judges": "Stone"}, "Douglas v. Willcuts": {"id": "102484", "case_name": "Douglas v. Willcuts", "date": "1935-11-11", "judges": "Hughes"}, "Chesapeake & Ohio R. Co. v. United States": {"id": "102502", "case_name": "Chesapeake & Ohio R. Co. v. United States", "date": "1935-11-25", "judges": "Per Curiam"}, "Atchison, T. & SFR Co. v. United States": {"id": "102447", "case_name": "Atchison, T. & SFR Co. v. United States", "date": "1935-04-29", "judges": "Butler"}, "West Ohio Gas Co. v. Public Util. Comm'n of Ohio": {"id": "102369", "case_name": "West Ohio Gas Co. v. Public Util. Comm'n of Ohio", "date": "1935-01-07", "judges": "Cardozo"}, "Adams v. Champion": {"id": "102386", "case_name": "Adams v. Champion", "date": "1935-02-04", "judges": "Cardozo"}, "Nathan Amchanitzky v. The United States.": {"id": "102555", "case_name": "Nathan Amchanitzky v. The United States.", "date": "1935-10-14", "judges": ""}, "Panhandle Co. v. Highway Comm'n.": {"id": "102410", "case_name": "Panhandle Co. v. Highway Comm'n.", "date": "1935-04-01", "judges": "McReynolds"}, "Guy T. Helvering, Commissioner of Internal Revenue v. Francis J. Stokes.": {"id": "102543", "case_name": "Guy T. Helvering, Commissioner of Internal Revenue v. Francis J. Stokes.", "date": "1935-12-09", "judges": ""}, "Metropolitan Casualty Ins. Co. v. Brownell": {"id": "102406", "case_name": "Metropolitan Casualty Ins. Co. v. Brownell", "date": "1935-03-18", "judges": "Stone"}, "Del Vecchio v. Bowers": {"id": "102514", "case_name": "Del Vecchio v. Bowers", "date": "1935-12-09", "judges": "Roberts"}, "Doleman v. Levine": {"id": "102451", "case_name": "Doleman v. Levine", "date": "1935-04-29", "judges": "Stone"}, "United States v. Constantine": {"id": "102515", "case_name": "United States v. Constantine", "date": "1935-12-09", "judges": "Roberts"}, "Hartley v. Commissioner": {"id": "102450", "case_name": "Hartley v. Commissioner", "date": "1935-05-20", "judges": "Stone"}, "Guy T. Helvering, Commissioner of Internal Revenue v. Edmund O. Schweitzer.": {"id": "102542", "case_name": "Guy T. Helvering, Commissioner of Internal Revenue v. Edmund O. Schweitzer.", "date": "1935-12-09", "judges": ""}, "Norris v. Alabama": {"id": "102407", "case_name": "Norris v. Alabama", "date": "1935-04-01", "judges": "Hughes"}, "Cooney v. Mountain States Telephone & Telegraph Co.": {"id": "102391", "case_name": "Cooney v. Mountain States Telephone & Telegraph Co.", "date": "1935-03-04", "judges": "Hughes"}, "Robert G. Stone and Carrie M. Stone, Trustees Under Will of Galen L. Stone v. Thomas W. White, Former Collector of Internal Revenue at Boston, Massachusetts.": {"id": "102554", "case_name": "Robert G. Stone and Carrie M. Stone, Trustees Under Will of Galen L. Stone v. Thomas W. White, Former Collector of Internal Revenue at Boston, Massachusetts.", "date": "1935-10-14", "judges": ""}, "Henry L. Doherty & Co. v. Goodman": {"id": "102411", "case_name": "Henry L. Doherty & Co. v. Goodman", "date": "1935-04-01", "judges": "McReynolds"}, "United States Ex Rel. Chicago Great Western R. Co. v. ICC": {"id": "102368", "case_name": "United States Ex Rel. Chicago Great Western R. Co. v. ICC", "date": "1935-01-07", "judges": "Roberts"}, "Norman v. Baltimore & Ohio R. Co.": {"id": "102387", "case_name": "Norman v. Baltimore & Ohio R. Co.", "date": "1935-02-18", "judges": "Hughes"}, "United States v. Hastings": {"id": "102503", "case_name": "United States v. Hastings", "date": "1935-12-09", "judges": "Hughes"}, "United States v. Arizona": {"id": "102446", "case_name": "United States v. Arizona", "date": "1935-04-29", "judges": "Butler"}, "Borax Consol., Ltd. v. Los Angeles": {"id": "102485", "case_name": "Borax Consol., Ltd. v. Los Angeles", "date": "1935-11-11", "judges": "Hughes"}, "Becker Steel Co. of America v. Cummings": {"id": "102493", "case_name": "Becker Steel Co. of America v. Cummings", "date": "1935-11-11", "judges": "Stone"}, "Lerner v. First Wis. Nat. Bank of Milwaukee": {"id": "2382138", "case_name": "Lerner v. First Wis. Nat. Bank of Milwaukee", "date": "1935-02-04", "judges": "McReynolds"}, "Adamos v. New York Life Ins. Co.": {"id": "102352", "case_name": "Adamos v. New York Life Ins. Co.", "date": "1935-01-07", "judges": "Hughes"}, "Morrissey v. Commissioner": {"id": "102519", "case_name": "Morrissey v. Commissioner", "date": "1935-12-16", "judges": "Hughes"}, "Mooney v. Holohan": {"id": "102372", "case_name": "Mooney v. Holohan", "date": "1935-01-21", "judges": "Per Curiam"}, "Waxham v. Smith": {"id": "102364", "case_name": "Waxham v. Smith", "date": "1935-01-07", "judges": "Stone"}, "Arthur O'TOOle v. State of New Jersey.": {"id": "102558", "case_name": "Arthur O'TOOle v. State of New Jersey.", "date": "1935-10-14", "judges": ""}, "Grovey v. Townsend": {"id": "102431", "case_name": "Grovey v. Townsend", "date": "1935-04-01", "judges": "Roberts"}, "Southern Pacific Company, a Corporation v. Leila Mae Walton, Administratrix, Etc.": {"id": "102574", "case_name": "Southern Pacific Company, a Corporation v. Leila Mae Walton, Administratrix, Etc.", "date": "1935-12-09", "judges": ""}, "Superintendent of Five Civilized Tribes v. Commissioner": {"id": "102466", "case_name": "Superintendent of Five Civilized Tribes v. Commissioner", "date": "1935-05-20", "judges": "McReynolds"}, "John A. Nelson Co. v. Helvering": {"id": "102523", "case_name": "John A. Nelson Co. v. Helvering", "date": "1935-12-16", "judges": "McReynolds"}, "Becker v. St. Louis Union Trust Co.": {"id": "102489", "case_name": "Becker v. St. Louis Union Trust Co.", "date": "1935-11-11", "judges": "Sutherland"}, "United States v. West Virginia": {"id": "102470", "case_name": "United States v. West Virginia", "date": "1935-05-20", "judges": "Stone"}, "Rose Hudson Barnes v. Frances D. Boyd, Annie L. Brown": {"id": "102427", "case_name": "Rose Hudson Barnes v. Frances D. Boyd, Annie L. Brown", "date": "1935-03-18", "judges": ""}, "John Wilson Brown, III v. Gesellschaft Fur Drahtlose Telegraphie, M. B. H., a Corporation.": {"id": "102562", "case_name": "John Wilson Brown, III v. Gesellschaft Fur Drahtlose Telegraphie, M. B. H., a Corporation.", "date": "1935-10-14", "judges": ""}, "United States v. Baltimore & Ohio R. Co.": {"id": "102355", "case_name": "United States v. Baltimore & Ohio R. Co.", "date": "1935-01-07", "judges": "Brandeis"}, "H. Newkirk Wheeler v. Robert E. Clark, United States Marshal, Etc.": {"id": "102569", "case_name": "H. Newkirk Wheeler v. Robert E. Clark, United States Marshal, Etc.", "date": "1935-10-28", "judges": ""}, "Helvering v. City Bank Farmers Trust Co.": {"id": "102494", "case_name": "Helvering v. City Bank Farmers Trust Co.", "date": "1935-11-11", "judges": "Roberts"}, "The State of New Jersey v. The State of Delaware": {"id": "102482", "case_name": "The State of New Jersey v. The State of Delaware", "date": "1935-06-03", "judges": ""}, "Hill v. Martin": {"id": "102528", "case_name": "Hill v. Martin", "date": "1935-12-16", "judges": "Brandeis"}, "General Util. & Operating Co. v. Helvering": {"id": "102504", "case_name": "General Util. & Operating Co. v. Helvering", "date": "1935-12-09", "judges": "McReynolds"}, "Hallenbeck v. Leimert": {"id": "102441", "case_name": "Hallenbeck v. Leimert", "date": "1935-04-29", "judges": "McReynolds"}, "Penn Central Casualty Co. v. Pennsylvania Ex Rel. Schnader": {"id": "102380", "case_name": "Penn Central Casualty Co. v. Pennsylvania Ex Rel. Schnader", "date": "1935-02-04", "judges": "Stone"}, "Winthrop Taylor v. Commissioner of Internal Revenue.": {"id": "102553", "case_name": "Winthrop Taylor v. Commissioner of Internal Revenue.", "date": "1935-10-14", "judges": ""}, "W. Verdner Carson, Frank R. Atwill v. The Long-Bell Lumber Corporation": {"id": "102416", "case_name": "W. Verdner Carson, Frank R. Atwill v. The Long-Bell Lumber Corporation", "date": "1935-01-21", "judges": ""}, "Pennsylvania v. Williams": {"id": "102379", "case_name": "Pennsylvania v. Williams", "date": "1935-02-04", "judges": "Stone"}, "Schoenamsgruber v. Hamburg American Line": {"id": "102396", "case_name": "Schoenamsgruber v. Hamburg American Line", "date": "1935-02-08", "judges": "Butler"}, "The United States of America v. Frank Rizzo, of 146,157 Gallons of Alcohol. 1": {"id": "102545", "case_name": "The United States of America v. Frank Rizzo, of 146,157 Gallons of Alcohol. 1", "date": "1935-10-14", "judges": ""}, "The Ansaldo San Giorgio I v. Rheinstrom Brothers Co.": {"id": "102400", "case_name": "The Ansaldo San Giorgio I v. Rheinstrom Brothers Co.", "date": "1935-03-04", "judges": "Roberts"}, "Clyde Mallory Lines v. Alabama Ex Rel. State Docks Comm'n": {"id": "102512", "case_name": "Clyde Mallory Lines v. Alabama Ex Rel. State Docks Comm'n", "date": "1935-12-09", "judges": "Stone"}, "Aero Transit Co. v. Georgia Comm'n.": {"id": "102457", "case_name": "Aero Transit Co. v. Georgia Comm'n.", "date": "1935-04-29", "judges": "Cardozo"}, "James Steele v. The People of the State of New York.": {"id": "102420", "case_name": "James Steele v. The People of the State of New York.", "date": "1935-02-11", "judges": ""}, "Holmes Hall v. Universal Oil Products Company": {"id": "102565", "case_name": "Holmes Hall v. Universal Oil Products Company", "date": "1935-10-14", "judges": ""}, "United States v. Spaulding": {"id": "102359", "case_name": "United States v. Spaulding", "date": "1935-01-07", "judges": "Butler"}, "Ickes v. Virginia-Colorado Development Corp.": {"id": "102477", "case_name": "Ickes v. Virginia-Colorado Development Corp.", "date": "1935-06-03", "judges": "Hughes"}, "Schuylkill Trust Co. v. Pennsylvania": {"id": "102498", "case_name": "Schuylkill Trust Co. v. Pennsylvania", "date": "1935-11-11", "judges": "Roberts"}, "Radio Corp. of America v. Raytheon Mfg. Co.": {"id": "102532", "case_name": "Radio Corp. of America v. Raytheon Mfg. Co.", "date": "1935-12-23", "judges": "Cardozo"}, "Peters Patent Corp. v. Bates & Klinke, Inc.": {"id": "102461", "case_name": "Peters Patent Corp. v. Bates & Klinke, Inc.", "date": "1935-05-13", "judges": "Per Curiam"}, "Helvering v. Minnesota Tea Co.": {"id": "102524", "case_name": "Helvering v. Minnesota Tea Co.", "date": "1935-12-16", "judges": "McReynolds"}, "Berger v. United States": {"id": "102436", "case_name": "Berger v. United States", "date": "1935-04-15", "judges": "Sutherland"}, "Rebecca F. Jones v. Jefferson Standard Life Insurance Company.": {"id": "102573", "case_name": "Rebecca F. Jones v. Jefferson Standard Life Insurance Company.", "date": "1935-12-09", "judges": ""}, "Alexander v. Hillman": {"id": "102508", "case_name": "Alexander v. Hillman", "date": "1935-12-09", "judges": "Butler"}, "Smith v. Snow": {"id": "102363", "case_name": "Smith v. Snow", "date": "1935-01-07", "judges": "Stone"}, "Vivian Wycliffe Buie v. The United States of America.": {"id": "102549", "case_name": "Vivian Wycliffe Buie v. The United States of America.", "date": "1935-10-14", "judges": ""}, "Helvering v. Grinnell": {"id": "102375", "case_name": "Helvering v. Grinnell", "date": "1935-02-04", "judges": "Sutherland"}, "Jurney v. MacCracken": {"id": "102374", "case_name": "Jurney v. MacCracken", "date": "1935-02-04", "judges": "Brandeis"}, "Georgia M. Spruill v. William T. Ballard, Abram R. Serven, William D. Buck": {"id": "102548", "case_name": "Georgia M. Spruill v. William T. Ballard, Abram R. Serven, William D. Buck", "date": "1935-10-14", "judges": ""}, "Klamath v. United States": {"id": "102509", "case_name": "Klamath v. United States", "date": "1935-12-09", "judges": "Butler"}, "Spielman Motor Sales Co. v. Dodge": {"id": "102437", "case_name": "Spielman Motor Sales Co. v. Dodge", "date": "1935-04-29", "judges": "Hughes"}, "A. J. Richardson v. Chicago, Rock Island & Gulf Railway Company.": {"id": "102572", "case_name": "A. J. Richardson v. Chicago, Rock Island & Gulf Railway Company.", "date": "1935-12-09", "judges": ""}, "Railroad Retirement Bd. v. Alton R. Co.": {"id": "102460", "case_name": "Railroad Retirement Bd. v. Alton R. Co.", "date": "1935-05-06", "judges": "Roberts"}, "Helvering v. Watts": {"id": "102525", "case_name": "Helvering v. Watts", "date": "1935-12-16", "judges": "McReynolds"}, "Mobley v. New York Life Ins. Co.": {"id": "102476", "case_name": "Mobley v. New York Life Ins. Co.", "date": "1935-05-27", "judges": "Butler"}, "American Surety Co. v. Westinghouse Elec. Mfg. Co.": {"id": "102499", "case_name": "American Surety Co. v. Westinghouse Elec. Mfg. Co.", "date": "1935-11-11", "judges": "Cardozo"}, "Dimick v. Schiedt": {"id": "102358", "case_name": "Dimick v. Schiedt", "date": "1935-01-07", "judges": "Sutherland"}, "Georgia M. Spruill v. Howard E. Crawford.": {"id": "102421", "case_name": "Georgia M. Spruill v. Howard E. Crawford.", "date": "1935-02-18", "judges": ""}, "A. G. Triplett, R. M. Triplett, A. Nelson v. Percival D. Lowell, Francis W. Dunmore, and Dubilier Condenser Corporation.": {"id": "102564", "case_name": "A. G. Triplett, R. M. Triplett, A. Nelson v. Percival D. Lowell, Francis W. Dunmore, and Dubilier Condenser Corporation.", "date": "1935-10-14", "judges": ""}, "Milwaukee County v. ME White Co.": {"id": "102513", "case_name": "Milwaukee County v. ME White Co.", "date": "1935-12-09", "judges": "Stone"}, "Roberts v. New York City": {"id": "102456", "case_name": "Roberts v. New York City", "date": "1935-04-29", "judges": "Cardozo"}, "St. Louis Can Company v. General American Life Insurance Company": {"id": "102544", "case_name": "St. Louis Can Company v. General American Life Insurance Company", "date": "1935-10-14", "judges": ""}, "United States v. Chicago, M., St. P. & PR Co.": {"id": "102401", "case_name": "United States v. Chicago, M., St. P. & PR Co.", "date": "1935-03-04", "judges": "Cardozo"}, "Fox v. Standard Oil Co. of NJ": {"id": "2382407", "case_name": "Fox v. Standard Oil Co. of NJ", "date": "1935-01-14", "judges": "Cardozo"}, "Wiloil Corp. v. Pennsylvania": {"id": "102378", "case_name": "Wiloil Corp. v. Pennsylvania", "date": "1935-02-04", "judges": "Butler"}, "Great Northern R. Co. v. Sullivan": {"id": "102397", "case_name": "Great Northern R. Co. v. Sullivan", "date": "1935-03-04", "judges": "Butler"}, "Y. Allen Holman, Sudie D. Holman, J. D. Holman v. Gulf Refining Company of Louisiana": {"id": "102552", "case_name": "Y. Allen Holman, Sudie D. Holman, J. D. Holman v. Gulf Refining Company of Louisiana", "date": "1935-10-14", "judges": ""}, "Anthony J. Drexel Biddle, Jr. v. Irving Trust Company, as Trustee, Etc.": {"id": "102417", "case_name": "Anthony J. Drexel Biddle, Jr. v. Irving Trust Company, as Trustee, Etc.", "date": "1935-02-04", "judges": ""}, "Domenech v. National City Bank of NY": {"id": "102381", "case_name": "Domenech v. National City Bank of NY", "date": "1935-02-04", "judges": "Roberts"}, "Fox Film Corp. v. Muller": {"id": "102505", "case_name": "Fox Film Corp. v. Muller", "date": "1935-12-09", "judges": "Sutherland"}, "Van Wart v. Commissioner": {"id": "102440", "case_name": "Van Wart v. Commissioner", "date": "1935-04-29", "judges": "McReynolds"}, "United States v. The State of Oregon": {"id": "102483", "case_name": "United States v. The State of Oregon", "date": "1935-06-03", "judges": ""}, "Colgate v. Harvey": {"id": "102529", "case_name": "Colgate v. Harvey", "date": "1935-12-16", "judges": "Sutherland"}, "Helvering v. Helmholz": {"id": "102495", "case_name": "Helvering v. Helmholz", "date": "1935-11-11", "judges": "Roberts"}, "James v. Allred, Governor of State of Texas v. Stanolind Oil & Gas Company": {"id": "102568", "case_name": "James v. Allred, Governor of State of Texas v. Stanolind Oil & Gas Company", "date": "1935-10-21", "judges": ""}, "Shanferoke Coal & Supply Corp. v. Westchester Service Corp.": {"id": "102354", "case_name": "Shanferoke Coal & Supply Corp. v. Westchester Service Corp.", "date": "1935-01-07", "judges": "Brandeis"}, "Bull v. United States": {"id": "102455", "case_name": "Bull v. United States", "date": "1935-04-29", "judges": "Roberts"}, "Miller v. Irving Trust Co.": {"id": "102510", "case_name": "Miller v. Irving Trust Co.", "date": "1935-12-09", "judges": "Butler"}, "Baldwin v. GAF Seelig, Inc.": {"id": "102402", "case_name": "Baldwin v. GAF Seelig, Inc.", "date": "1935-03-04", "judges": "Cardozo"}, "Justus B. Linderholm v. The State of Kansas.": {"id": "102547", "case_name": "Justus B. Linderholm v. The State of Kansas.", "date": "1935-10-14", "judges": ""}, "Miller v. United States": {"id": "102394", "case_name": "Miller v. United States", "date": "1935-03-04", "judges": "Sutherland"}, "Helvering v. Inter-Mountain Life Ins. Co.": {"id": "102414", "case_name": "Helvering v. Inter-Mountain Life Ins. Co.", "date": "1935-01-21", "judges": "Butler"}, "Realty Acceptance Corporation v. Henry G. Montgomery.": {"id": "102551", "case_name": "Realty Acceptance Corporation v. Henry G. Montgomery.", "date": "1935-10-14", "judges": ""}, "Douglas v. Cunningham": {"id": "102382", "case_name": "Douglas v. Cunningham", "date": "1935-02-04", "judges": "Roberts"}, "Snyder v. Commissioner": {"id": "102443", "case_name": "Snyder v. Commissioner", "date": "1935-04-29", "judges": "Brandeis"}, "Bingham v. United States": {"id": "102506", "case_name": "Bingham v. United States", "date": "1935-12-09", "judges": "Sutherland"}, "Wilshire Oil Co. v. United States": {"id": "102438", "case_name": "Wilshire Oil Co. v. United States", "date": "1935-04-29", "judges": "Per Curiam"}, "Baltimore & Carolina Line, Inc. v. Redman": {"id": "102480", "case_name": "Baltimore & Carolina Line, Inc. v. Redman", "date": "1935-06-03", "judges": "Van Devanter"}, "White v. Poor": {"id": "102496", "case_name": "White v. Poor", "date": "1935-11-11", "judges": "Roberts"}, "The Admiral Peoples": {"id": "102479", "case_name": "The Admiral Peoples", "date": "1935-06-03", "judges": "Hughes"}, "Taylor v. Sternberg": {"id": "102357", "case_name": "Taylor v. Sternberg", "date": "1935-01-07", "judges": "Sutherland"}, "Atlantic Coast Line R. Co. v. Florida": {"id": "102459", "case_name": "Atlantic Coast Line R. Co. v. Florida", "date": "1935-04-29", "judges": "Cardozo"}, "Paramount Publix Corp. v. American Tri-Ergon Corp.": {"id": "102398", "case_name": "Paramount Publix Corp. v. American Tri-Ergon Corp.", "date": "1935-03-04", "judges": "Stone"}, "Seabury v. Green": {"id": "102377", "case_name": "Seabury v. Green", "date": "1935-02-04", "judges": "Butler"}, "Jesse C. Duke v. The Committee on Grievances of the Supreme Court of the District of Columbia": {"id": "102418", "case_name": "Jesse C. Duke v. The Committee on Grievances of the Supreme Court of the District of Columbia", "date": "1935-02-04", "judges": ""}, "Washburn Crosby Company v. Dan M. Lee, Individually and as Collector, Etc.": {"id": "102571", "case_name": "Washburn Crosby Company v. Dan M. Lee, Individually and as Collector, Etc.", "date": "1935-11-11", "judges": ""}, "Fox v. Gulf Refining Co.": {"id": "102434", "case_name": "Fox v. Gulf Refining Co.", "date": "1935-04-08", "judges": "Per Curiam"}, "G. & K. Mfg. Co. v. Helvering": {"id": "102526", "case_name": "G. & K. Mfg. Co. v. Helvering", "date": "1935-12-16", "judges": "McReynolds"}, "Texas & New Orleans R. Co. v. United States": {"id": "102463", "case_name": "Texas & New Orleans R. Co. v. United States", "date": "1935-05-13", "judges": "Per Curiam"}, "United States v. Halsey, Stuart & Co.": {"id": "102530", "case_name": "United States v. Halsey, Stuart & Co.", "date": "1935-12-23", "judges": "Per Curiam"}, "Humphrey's v. United States": {"id": "102475", "case_name": "Humphrey's v. United States", "date": "1935-05-27", "judges": "Sutherland"}, "Jacksonville Terminal Company v. Geneva Blackshear, as Administratrix, Etc.": {"id": "102567", "case_name": "Jacksonville Terminal Company v. Geneva Blackshear, as Administratrix, Etc.", "date": "1935-10-21", "judges": ""}, "Carl Green v. The Cleveland, Cincinnati, Chicago, and St. Louis Railway Company.": {"id": "102422", "case_name": "Carl Green v. The Cleveland, Cincinnati, Chicago, and St. Louis Railway Company.", "date": "1935-02-18", "judges": ""}, "The State of Missouri, at the Relation of Weightstill Woods v. Hon. Nike G. Sevier.": {"id": "102566", "case_name": "The State of Missouri, at the Relation of Weightstill Woods v. Hon. Nike G. Sevier.", "date": "1935-10-21", "judges": ""}, "Joseph Ziccardi v. Travelers Insurance Company and Lenox Operating Company.": {"id": "102423", "case_name": "Joseph Ziccardi v. Travelers Insurance Company and Lenox Operating Company.", "date": "1935-02-18", "judges": ""}, "Motlow v. State Ex Rel. Koeln": {"id": "2513953", "case_name": "Motlow v. State Ex Rel. Koeln", "date": "1935-04-29", "judges": "Per Curiam"}, "Corporation Comm'n of Okla. v. Cary": {"id": "102531", "case_name": "Corporation Comm'n of Okla. v. Cary", "date": "1935-12-23", "judges": "Per Curiam"}, "ALA Schechter Poultry Corp. v. United States": {"id": "102474", "case_name": "ALA Schechter Poultry Corp. v. United States", "date": "1935-05-27", "judges": "Hughes"}, "Bus & Transport Securities Corporation v. Helvering, Commissioner of Internal Revenue": {"id": "102527", "case_name": "Bus & Transport Securities Corporation v. Helvering, Commissioner of Internal Revenue", "date": "1935-12-16", "judges": ""}, "Hollins v. Oklahoma": {"id": "102462", "case_name": "Hollins v. Oklahoma", "date": "1935-05-13", "judges": "Per Curiam"}, "Tracy C. Drake, John B. Drake v. Metropolitan Life Insurance Company": {"id": "102570", "case_name": "Tracy C. Drake, John B. Drake v. Metropolitan Life Insurance Company", "date": "1935-10-28", "judges": ""}, "Stanley v. Public Util. Comm'n": {"id": "102435", "case_name": "Stanley v. Public Util. Comm'n", "date": "1935-04-15", "judges": "Per Curiam"}, "Anders Jordahl and Mary D. Jordahl v. Irving Trust Company, Trustee in Bankruptcy of International Match Corporation, Etc.": {"id": "102419", "case_name": "Anders Jordahl and Mary D. Jordahl v. Irving Trust Company, Trustee in Bankruptcy of International Match Corporation, Etc.", "date": "1935-02-04", "judges": ""}, "Helvering v. Taylor": {"id": "102360", "case_name": "Helvering v. Taylor", "date": "1935-01-07", "judges": "Butler"}, "Altoona Publix Theatres, Inc. v. American Tri-Ergon Corp.": {"id": "102399", "case_name": "Altoona Publix Theatres, Inc. v. American Tri-Ergon Corp.", "date": "1935-03-04", "judges": "Stone"}, "Forrest v. Jack": {"id": "102376", "case_name": "Forrest v. Jack", "date": "1935-02-04", "judges": "Butler"}, "Realty Associates Securities Corp. v. O'Connor": {"id": "102458", "case_name": "Realty Associates Securities Corp. v. O'Connor", "date": "1935-04-29", "judges": "Cardozo"}, "Gregory v. Helvering": {"id": "102356", "case_name": "Gregory v. Helvering", "date": "1935-01-07", "judges": "Sutherland"}, "McFeely v. Commissioner": {"id": "102497", "case_name": "McFeely v. Commissioner", "date": "1935-11-11", "judges": "Roberts"}, "Minnie v. Port Huron Terminal Co.": {"id": "102478", "case_name": "Minnie v. Port Huron Terminal Co.", "date": "1935-06-03", "judges": "Hughes"}, "West v. Chesapeake & Potomac Telephone Co. of Baltimore": {"id": "102481", "case_name": "West v. Chesapeake & Potomac Telephone Co. of Baltimore", "date": "1935-06-03", "judges": "Roberts"}, "United States v. Creek Nation": {"id": "102439", "case_name": "United States v. Creek Nation", "date": "1935-04-29", "judges": "Van Devanter"}, "Helvering v. Rankin": {"id": "102442", "case_name": "Helvering v. Rankin", "date": "1935-04-29", "judges": "Brandeis"}, "Industrial Trust Co. v. United States": {"id": "102507", "case_name": "Industrial Trust Co. v. United States", "date": "1935-12-09", "judges": "Sutherland"}, "Clark v. Williard": {"id": "102383", "case_name": "Clark v. Williard", "date": "1935-02-04", "judges": "Cardozo"}, "Georgia M. Spruill v. Mary O'TOOle and Edgar C. Snyder.": {"id": "102415", "case_name": "Georgia M. Spruill v. Mary O'TOOle and Edgar C. Snyder.", "date": "1935-01-14", "judges": ""}, "People of the State of New York, Ex Rel. Federal Motor Truck Co., of New York, Inc. v. Thomas M. Lynch, as and Constituting the State Tax Commission of New York.": {"id": "102550", "case_name": "People of the State of New York, Ex Rel. Federal Motor Truck Co., of New York, Inc. v. Thomas M. Lynch, as and Constituting the State Tax Commission of New York.", "date": "1935-10-14", "judges": ""}, "Manufacturers' Finance Co. v. McKey": {"id": "102395", "case_name": "Manufacturers' Finance Co. v. McKey", "date": "1935-03-04", "judges": "Sutherland"}, "Swinson v. Chicago, St. P., M. & OR Co.": {"id": "102403", "case_name": "Swinson v. Chicago, St. P., M. & OR Co.", "date": "1935-03-11", "judges": "Brandeis"}, "A. G. Triplett v. Percival D. Lowell": {"id": "102546", "case_name": "A. G. Triplett v. Percival D. Lowell", "date": "1935-12-09", "judges": ""}, "Ivanhoe Building & Loan Assn. v. Orr": {"id": "102454", "case_name": "Ivanhoe Building & Loan Assn. v. Orr", "date": "1935-04-29", "judges": "Roberts"}, "New Jersey v. New York City": {"id": "102511", "case_name": "New Jersey v. New York City", "date": "1935-12-09", "judges": "Decree"}, "Detroit Bridge Co. v. Tax Board": {"id": "102371", "case_name": "Detroit Bridge Co. v. Tax Board", "date": "1935-01-14", "judges": "McReynolds"}, "Patterson v. Alabama": {"id": "102408", "case_name": "Patterson v. Alabama", "date": "1935-04-01", "judges": "Hughes"}, "Nortz v. United States": {"id": "102388", "case_name": "Nortz v. United States", "date": "1935-02-18", "judges": "Hughes"}, "Keystone Driller Co. v. Northwest Engineering Corp.": {"id": "102367", "case_name": "Keystone Driller Co. v. Northwest Engineering Corp.", "date": "1935-01-07", "judges": "Roberts"}, "Kimen v. Atlas Exchange Nat. Bank of Chicago": {"id": "102449", "case_name": "Kimen v. Atlas Exchange Nat. Bank of Chicago", "date": "1935-04-29", "judges": "Stone"}, "Worthen Co. v. Kavanaugh": {"id": "102432", "case_name": "Worthen Co. v. Kavanaugh", "date": "1935-04-01", "judges": "Cardozo"}, "Swanson v. Commissioner": {"id": "102520", "case_name": "Swanson v. Commissioner", "date": "1935-12-16", "judges": "Hughes"}, "Stewart v. Keyes": {"id": "102465", "case_name": "Stewart v. Keyes", "date": "1935-05-20", "judges": "Van Devanter"}, "Louisville Joint Stock Land Bank v. Radford": {"id": "2513954", "case_name": "Louisville Joint Stock Land Bank v. Radford", "date": "1935-05-27", "judges": "Brandeis"}, "Escoe v. Zerbst": {"id": "102473", "case_name": "Escoe v. Zerbst", "date": "1935-05-20", "judges": "Cardozo"}, "Continental Illinois National Bank & Trust Company of Chicago v. Columbian National Life Insurance Company.": {"id": "102561", "case_name": "Continental Illinois National Bank & Trust Company of Chicago v. Columbian National Life Insurance Company.", "date": "1935-10-14", "judges": ""}, "Eric Lyders v. Inger Marie Petersen, Maren Jensen, Johannes Nielsen": {"id": "102424", "case_name": "Eric Lyders v. Inger Marie Petersen, Maren Jensen, Johannes Nielsen", "date": "1935-03-11", "judges": ""}, "Stelos Co. v. Hosiery Motor-Mend Corp.": {"id": "102453", "case_name": "Stelos Co. v. Hosiery Motor-Mend Corp.", "date": "1935-04-29", "judges": "Roberts"}, "United States v. Kesterson": {"id": "102516", "case_name": "United States v. Kesterson", "date": "1935-12-09", "judges": "Roberts"}, "Alaska Packers Assn. v. Industrial Accident Comm'n of Cal.": {"id": "102404", "case_name": "Alaska Packers Assn. v. Industrial Accident Comm'n of Cal.", "date": "1935-03-11", "judges": "Stone"}, "George Allison & Co., Inc. v. The United States of America, and Interstate Commerce Commission.": {"id": "102541", "case_name": "George Allison & Co., Inc. v. The United States of America, and Interstate Commerce Commission.", "date": "1935-11-11", "judges": ""}, "Aktieselskabet Cuzco v. the Sucarseco": {"id": "102392", "case_name": "Aktieselskabet Cuzco v. the Sucarseco", "date": "1935-03-04", "judges": "Hughes"}, "Broderick v. Rosner": {"id": "102412", "case_name": "Broderick v. Rosner", "date": "1935-04-01", "judges": "Brandeis"}, "Gordon v. Ominsky": {"id": "2382382", "case_name": "Gordon v. Ominsky", "date": "1935-02-04", "judges": "Stone"}, "Anne M. Evans v. Missouri State Life Insurance Company.": {"id": "102557", "case_name": "Anne M. Evans v. Missouri State Life Insurance Company.", "date": "1935-10-14", "judges": ""}, "Jennings v. United States Fidelity & Guaranty Co.": {"id": "102384", "case_name": "Jennings v. United States Fidelity & Guaranty Co.", "date": "1935-02-04", "judges": "Cardozo"}, "Georgia R. & Elec. Co. v. Decatur": {"id": "102445", "case_name": "Georgia R. & Elec. Co. v. Decatur", "date": "1935-04-29", "judges": "Sutherland"}, "McCandless v. Furlaud": {"id": "102500", "case_name": "McCandless v. Furlaud", "date": "1935-11-11", "judges": "Cardozo"}, "Graham v. White-Phillips Co.": {"id": "102486", "case_name": "Graham v. White-Phillips Co.", "date": "1935-11-11", "judges": "McReynolds"}, "Wisconsin v. Michigan": {"id": "102469", "case_name": "Wisconsin v. Michigan", "date": "1935-05-20", "judges": "Butler"}, "Chandler Co. v. Brandtjen, Inc.": {"id": "102490", "case_name": "Chandler Co. v. Brandtjen, Inc.", "date": "1935-11-11", "judges": "Butler"}, "United States v. Oregon": {"id": "102428", "case_name": "United States v. Oregon", "date": "1935-04-01", "judges": "Stone"}, "Enelow v. New York Life Ins. Co.": {"id": "102351", "case_name": "Enelow v. New York Life Ins. Co.", "date": "1935-01-07", "judges": "Hughes"}, "Gordon v. Washington": {"id": "102429", "case_name": "Gordon v. Washington", "date": "1935-04-01", "judges": "Stone"}, "Raybestos-Manhattan Co. v. United States": {"id": "102491", "case_name": "Raybestos-Manhattan Co. v. United States", "date": "1935-11-11", "judges": "Stone"}, "Atlanta, B. & CR Co. v. United States": {"id": "102487", "case_name": "Atlanta, B. & CR Co. v. United States", "date": "1935-11-11", "judges": "Brandeis"}, "Herndon v. Georgia": {"id": "102468", "case_name": "Herndon v. Georgia", "date": "1935-05-20", "judges": "Sutherland"}, "California Oregon Power Co. v. Beaver Portland Cement Co.": {"id": "102444", "case_name": "California Oregon Power Co. v. Beaver Portland Cement Co.", "date": "1935-04-29", "judges": "Sutherland"}, "Pacific States Box & Basket Co. v. White": {"id": "102501", "case_name": "Pacific States Box & Basket Co. v. White", "date": "1935-11-18", "judges": "Brandeis"}, "Old Company's Lehigh, Inc. v. Meeker": {"id": "102385", "case_name": "Old Company's Lehigh, Inc. v. Meeker", "date": "1935-02-04", "judges": "Cardozo"}, "Continental Bank v. Rock Island Ry.": {"id": "102413", "case_name": "Continental Bank v. Rock Island Ry.", "date": "1935-04-01", "judges": "Sutherland"}, "Standard Wholesale Phosphate and Acid Works, Inc. v. The General Chemical Company.": {"id": "102556", "case_name": "Standard Wholesale Phosphate and Acid Works, Inc. v. The General Chemical Company.", "date": "1935-10-14", "judges": ""}, "Nashville, C. & St. LR Co. v. Walters": {"id": "102393", "case_name": "Nashville, C. & St. LR Co. v. Walters", "date": "1935-03-04", "judges": "Brandeis"}, "Stewart Dry Goods Co. v. Lewis": {"id": "102405", "case_name": "Stewart Dry Goods Co. v. Lewis", "date": "1935-03-11", "judges": "Roberts"}, "Federal Land Bank v. Priddy": {"id": "102452", "case_name": "Federal Land Bank v. Priddy", "date": "1935-04-29", "judges": "Stone"}, "Hulburd v. Commissioner": {"id": "102517", "case_name": "Hulburd v. Commissioner", "date": "1935-12-09", "judges": "Cardozo"}, "Chicago Gravel Company v. Columbian National Life Insurance Company.": {"id": "102560", "case_name": "Chicago Gravel Company v. Columbian National Life Insurance Company.", "date": "1935-10-14", "judges": ""}, "Walter D. Price v. The United States of America.": {"id": "102425", "case_name": "Walter D. Price v. The United States of America.", "date": "1935-03-18", "judges": ""}, "United States v. MacK": {"id": "102472", "case_name": "United States v. MacK", "date": "1935-05-20", "judges": "Cardozo"}, "Helvering v. Combs": {"id": "102521", "case_name": "Helvering v. Combs", "date": "1935-12-16", "judges": "Hughes"}, "United States Ex Rel. Kassin v. Mulligan": {"id": "102464", "case_name": "United States Ex Rel. Kassin v. Mulligan", "date": "1935-05-13", "judges": "Butler"}, "Frank Collis Bowers, as of the Last Will and Testament of Frank K. Bowers, Deceased, Etc. v. The Farmers' Loan and Trust Company, as Trustee, Etc.": {"id": "102576", "case_name": "Frank Collis Bowers, as of the Last Will and Testament of Frank K. Bowers, Deceased, Etc. v. The Farmers' Loan and Trust Company, as Trustee, Etc.", "date": "1935-12-09", "judges": ""}, "Doty v. Love": {"id": "102433", "case_name": "Doty v. Love", "date": "1935-04-01", "judges": "Cardozo"}, "Awotin v. Atlas Exchange Nat. Bank of Chicago": {"id": "102448", "case_name": "Awotin v. Atlas Exchange Nat. Bank of Chicago", "date": "1935-04-29", "judges": "Stone"}, "Perry v. United States": {"id": "102389", "case_name": "Perry v. United States", "date": "1935-02-18", "judges": "Hughes"}, "Central Vt. Transp. Co. v. Durning": {"id": "102366", "case_name": "Central Vt. Transp. Co. v. Durning", "date": "1935-01-07", "judges": "Stone"}, "Semler v. Oregon Bd. of Dental Examiners": {"id": "102409", "case_name": "Semler v. Oregon Bd. of Dental Examiners", "date": "1935-04-01", "judges": "Hughes"}, "West Ohio Gas Co. v. Public Utilities Commission of Ohio": {"id": "102370", "case_name": "West Ohio Gas Co. v. Public Utilities Commission of Ohio", "date": "1935-01-07", "judges": ""}}